deepan_flask/__init__.py
deepan_flask/main.py
deepan_flask-0.2.dist-info/METADATA
deepan_flask-0.2.dist-info/WHEEL
deepan_flask-0.2.dist-info/top_level.txt
deepan_flask-0.2.dist-info/RECORD
