Metadata-Version: 2.1
Name: deepan_flask
Version: 0.2
